{"coordinateSystem":"Origin top-left; x increases right; y increases down; units are tiles.","mode":"intro","time":"12:00 AM","started":false,"player":{"x":10.5,"y":2.5,"moving":false,"room":"Study"},"roomBrief":"Mahogany shelves, lamplight, and enough corners to conceal a hurried lie.","conversation":null,"nearbyGuest":null,"visibleGuests":[{"id":8,"name":"Iris","x":10.5,"y":4.5,"moving":false,"activity":"roaming","goal":"standing by"}],"guestActivityCounts":{"roaming":10,"resting":0,"chatting":0},"visibleCorpses":[],"aliveGuests":10,"interviewedGuests":0,"discoveredBodies":0,"over":false,"ending":null,"objective":"Begin the case. Time will stay frozen until you move."}